{
  "date": "2026-07-23",
  "prev_date": "2026-07-22",
  "trends": {
    "西方奇幻": {
      "new_count": 1,
      "dropped_count": 1,
      "new_books": [
        "战争领主：万族之王"
      ],
      "dropped_books": [
        {
          "title": "军事公主不会爱上魔法科学家",
          "intro": "【西幻＋男女主双强＋魔导工业革命】 他是离经叛道的疯子教授，她是野心勃勃的铁腕公主。 在这个魔导工业革命兴起，旧贵族与新资本对撞的时代，当一本来自未来的【预言书】，将“死亡”的倒计时血淋淋地摆在他们面"
        }
      ],
      "top_risers": [
        {
          "title": "穿越自带炼妖壶：桀桀，顷刻炼化",
          "change": "+10"
        },
        {
          "title": "西幻：我有一本冒险者指南",
          "change": "+2"
        },
        {
          "title": "早知道不这么玩了！",
          "change": "+1"
        }
      ],
      "top_fallers": [
        {
          "title": "求生反派的魔女投资",
          "change": "-5"
        },
        {
          "title": "满级后，我在异世界当房东",
          "change": "-2"
        },
        {
          "title": "巫师：让你学知识，你杀穿万界？",
          "change": "-2"
        }
      ],
      "reads_growth": [
        {
          "title": "穿越自带炼妖壶：桀桀，顷刻炼化",
          "growth": "+1.5万"
        },
        {
          "title": "从零开始的黑暗童话世界",
          "growth": "+5000"
        },
        {
          "title": "求生反派的魔女投资",
          "growth": "+5000"
        }
      ],
      "summary": "新增1本上榜；1本掉出（《军事公主不会爱上魔法科学家》）；《穿越自带炼妖壶：桀桀，顷刻炼化》排名上升+10位；《穿越自带炼妖壶：桀桀，顷刻炼化》阅读量+1.5万。"
    },
    "东方仙侠": {
      "new_count": 0,
      "dropped_count": 0,
      "new_books": [],
      "dropped_books": [],
      "top_risers": [
        {
          "title": "帝域",
          "change": "+19"
        },
        {
          "title": "邪皇降世，从废物皇子开始",
          "change": "+2"
        },
        {
          "title": "被圣女推倒后，我无敌了",
          "change": "+2"
        }
      ],
      "top_fallers": [
        {
          "title": "西游：苟在猴哥体内满天神佛慌了",
          "change": "-6"
        },
        {
          "title": "西游：圣僧的自我修养",
          "change": "-3"
        },
        {
          "title": "我真不想修仙啊！",
          "change": "-2"
        }
      ],
      "reads_growth": [
        {
          "title": "邪皇降世，从废物皇子开始",
          "growth": "+2.8万"
        },
        {
          "title": "这！这是谁把杨婵放我府上的？",
          "growth": "+2.0万"
        },
        {
          "title": "帝域",
          "growth": "+1.4万"
        }
      ],
      "summary": "《帝域》排名上升+19位；《邪皇降世，从废物皇子开始》阅读量+2.8万。"
    },
    "科幻末世": {
      "new_count": 1,
      "dropped_count": 1,
      "new_books": [
        "全民求生，我能够自选宝箱奖励"
      ],
      "dropped_books": [
        {
          "title": "废土藏身处，从下水道开始升级",
          "intro": "【‘废土：文明堡垒’加载完成！幸存者资格激活。】 【幸存者于渊，初始区域抽取完毕！抽取结果为——暴乱街区】 意外进入废土世界的于渊，被迫开启了废土硬核生存之路。 在城市暴徒、极端天灾、玩家掠夺、文明入"
        }
      ],
      "top_risers": [
        {
          "title": "末日：我真不是土匪",
          "change": "+4"
        },
        {
          "title": "海洋求生：开局155加榴炮",
          "change": "+4"
        },
        {
          "title": "木筏求生，3S鱼竿带飞六个校花",
          "change": "+2"
        }
      ],
      "top_fallers": [
        {
          "title": "列车求生：每级一个彩色海克斯！",
          "change": "-2"
        },
        {
          "title": "盖楼求生，全公司女同事求我带飞",
          "change": "-2"
        },
        {
          "title": "庇护所进化论",
          "change": "-1"
        }
      ],
      "reads_growth": [
        {
          "title": "木筏求生，3S鱼竿带飞六个校花",
          "growth": "+1.8万"
        },
        {
          "title": "全民抽卡求生，每天一张传说卡",
          "growth": "+9000"
        },
        {
          "title": "末日：我真不是土匪",
          "growth": "+8000"
        }
      ],
      "summary": "新增1本上榜；1本掉出（《废土藏身处，从下水道开始升级》）；《末日：我真不是土匪》排名上升+4位；《木筏求生，3S鱼竿带飞六个校花》阅读量+1.8万。"
    },
    "都市日常": {
      "new_count": 1,
      "dropped_count": 1,
      "new_books": [
        "宦海浮沉"
      ],
      "dropped_books": [
        {
          "title": "妹妹吐槽魔鬼导师，我越听越心虚",
          "intro": "【慢热】+【单女主】+【无系统】+【日常】+【双向救赎】+【HE】 苏言有个秘密，他不仅谈过恋爱，前女友还是个智商160的绝顶天才。 三年后，亲妹考上江城大学研究生，天天在饭桌上吐槽： “哥！我们导师"
        }
      ],
      "top_risers": [
        {
          "title": "权利的游戏，从派出所民警开始",
          "change": "+15"
        },
        {
          "title": "北城枭雄",
          "change": "+2"
        },
        {
          "title": "重生2006，超级无敌爽爽爽。",
          "change": "+1"
        }
      ],
      "top_fallers": [
        {
          "title": "退伍归来，我的身份被妹妹曝光了",
          "change": "-7"
        },
        {
          "title": "彪悍人生：从川藏线带走老板娘开",
          "change": "-3"
        },
        {
          "title": "祖传风水师笔记",
          "change": "-3"
        }
      ],
      "reads_growth": [
        {
          "title": "穿到女频，整顿满城霸总",
          "growth": "+4.5万"
        },
        {
          "title": "权利的游戏，从派出所民警开始",
          "growth": "+3.1万"
        },
        {
          "title": "青梅暗恋我十年，还好我重生了",
          "growth": "+1.9万"
        }
      ],
      "summary": "新增1本上榜；1本掉出（《妹妹吐槽魔鬼导师，我越听越心虚》）；《权利的游戏，从派出所民警开始》排名上升+15位；《穿到女频，整顿满城霸总》阅读量+4.5万。"
    },
    "都市修真": {
      "new_count": 1,
      "dropped_count": 1,
      "new_books": [
        "每日一卦，天师练习生"
      ],
      "dropped_books": [
        {
          "title": "获得仙人传承，我在村里爽翻了",
          "intro": "乡村神医＋无敌暴爽＋美女全收 小村青年王长峰，只因为坏了村霸的好事，就被村霸打昏扔到了湖里，却没想到，王长峰非但没死，反而得了仙人传承。 从此，王长峰完成了蜕变，强大武力让四方臣服，逆天医术活死人肉白"
        }
      ],
      "top_risers": [
        {
          "title": "乡村神医，开局继承无敌传承",
          "change": "+6"
        },
        {
          "title": "半山村乡野神医",
          "change": "+4"
        },
        {
          "title": "杏花村神医赵老汉！",
          "change": "+4"
        }
      ],
      "top_fallers": [
        {
          "title": "山野神医杨水生，建设美好桃花村",
          "change": "-7"
        },
        {
          "title": "左手悬壶济世，右手持剑杀生",
          "change": "-4"
        },
        {
          "title": "乡村神医好快活",
          "change": "-2"
        }
      ],
      "reads_growth": [
        {
          "title": "离婚回村，丈母娘不想换女婿咋办",
          "growth": "+3.7万"
        },
        {
          "title": "半山村乡野神医",
          "growth": "+1.8万"
        },
        {
          "title": "749局：我一个邪修考编怎么了",
          "growth": "+1.0万"
        }
      ],
      "summary": "新增1本上榜；1本掉出（《获得仙人传承，我在村里爽翻了》）；《乡村神医，开局继承无敌传承》排名上升+6位；《离婚回村，丈母娘不想换女婿咋办》阅读量+3.7万。"
    },
    "都市高武": {
      "new_count": 2,
      "dropped_count": 2,
      "new_books": [
        "我为至尊，饲养八王猎诸神",
        "赛车娘世界：我有神级改装词条！"
      ],
      "dropped_books": [
        {
          "title": "自首后，国家发现我活了两千年",
          "intro": "捡到一本长生日记后，我决定冒充长生者自首。 结果第二天，我的眼睛变成了深渊................"
        },
        {
          "title": "别叫我恶魔",
          "intro": "神圣天门横立苍穹，时空魔渊涂炭人间，当大地涌出十二座灵泉，当月亮不再属于人类… 我们又将何去何从？ 神明的世界？恶魔的世界？ 不，这是属于人的世界！ 我将接过那无人扛起的冠冕，成为新时代的王。 我叫任"
        }
      ],
      "top_risers": [
        {
          "title": "游戏降临：我玩数值的练什么技巧",
          "change": "+11"
        },
        {
          "title": "开局地摊卖大力",
          "change": "+1"
        }
      ],
      "top_fallers": [
        {
          "title": "刚转职法师，技能成精了什么鬼？",
          "change": "-3"
        },
        {
          "title": "诡异难杀？抱歉，我才是真正不死",
          "change": "-2"
        },
        {
          "title": "我，亿万天赋，天才不过见我门槛",
          "change": "-1"
        }
      ],
      "reads_growth": [
        {
          "title": "诸神愚戏",
          "growth": "+14.5万"
        },
        {
          "title": "游戏降临：我玩数值的练什么技巧",
          "growth": "+2.4万"
        },
        {
          "title": "我在精神病院学斩神",
          "growth": "+1.5万"
        }
      ],
      "summary": "新增2本上榜；2本掉出（《自首后，国家发现我活了两千年》、《别叫我恶魔》）；《游戏降临：我玩数值的练什么技巧》排名上升+11位；《诸神愚戏》阅读量+14.5万。"
    },
    "历史古代": {
      "new_count": 0,
      "dropped_count": 0,
      "new_books": [],
      "dropped_books": [],
      "top_risers": [
        {
          "title": "大秦：开局扶苏被贬，忽悠他造反",
          "change": "+9"
        },
        {
          "title": "边军：从领取罪女开始，一统天下",
          "change": "+2"
        },
        {
          "title": "冒姓琅琊",
          "change": "+1"
        }
      ],
      "top_fallers": [
        {
          "title": "让你辅佐曹操，你天天骂他送死",
          "change": "-6"
        },
        {
          "title": "红楼之逍遥庶子无所谓",
          "change": "-2"
        },
        {
          "title": "贞观小闲王",
          "change": "-2"
        }
      ],
      "reads_growth": [
        {
          "title": "让你代写情书，你落笔惊哭大儒？",
          "growth": "+1.9万"
        },
        {
          "title": "冒姓琅琊",
          "growth": "+1.4万"
        },
        {
          "title": "国舅难当，这一世我只想躺平",
          "growth": "+1.2万"
        }
      ],
      "summary": "《大秦：开局扶苏被贬，忽悠他造反》排名上升+9位；《让你代写情书，你落笔惊哭大儒？》阅读量+1.9万。"
    },
    "战神赘婿": {
      "new_count": 1,
      "dropped_count": 1,
      "new_books": [
        "都市修罗狂婿"
      ],
      "dropped_books": [
        {
          "title": "赘婿复仇，麒麟上身，我无敌了！",
          "intro": "【不修炼，全文无敌➕师姐流➕爆燃爽文】 三年前，赘婿叶辰跟老婆沈傲雪去爬山，却被老婆推下山崖，生死不知。三年后，沈傲雪成了身价百亿的女神总裁，在老婆改嫁当天，叶辰强势归来！"
        }
      ],
      "top_risers": [
        {
          "title": "让你去历练，怎么全球都要活捉你",
          "change": "+2"
        },
        {
          "title": "隐居三年，出狱即无敌",
          "change": "+2"
        },
        {
          "title": "兵王：七个战友竟都是千金小姐！",
          "change": "+1"
        }
      ],
      "top_fallers": [
        {
          "title": "战神归隐新婚夜妻子却在陪干弟弟",
          "change": "-1"
        },
        {
          "title": "别又缘",
          "change": "-1"
        },
        {
          "title": "女总裁的特种小保安",
          "change": "-1"
        }
      ],
      "reads_growth": [
        {
          "title": "兵王之我是一个交警",
          "growth": "+6000"
        },
        {
          "title": "战神奶爸",
          "growth": "+4000"
        },
        {
          "title": "领证三天，我被未婚妻杀死",
          "growth": "+3000"
        }
      ],
      "summary": "新增1本上榜；1本掉出（《赘婿复仇，麒麟上身，我无敌了！》）；《让你去历练，怎么全球都要活捉你》排名上升+2位；《兵王之我是一个交警》阅读量+6000。"
    },
    "都市种田": {
      "new_count": 2,
      "dropped_count": 2,
      "new_books": [
        "年代1960：穿越南锣鼓巷，",
        "重生70我选择下乡"
      ],
      "dropped_books": [
        {
          "title": "60年代，为护着妹妹被迫下乡",
          "intro": "【单女主，空间，种田文，不暴力，生活类】 时代的洪流浩浩荡荡勇往向前，荡起灰尘落入千家万户，个人的命运随之身不由己。 面对一家人的愁云惨淡，带着熟练度面板和空间，身体数值一直提升的陆学文。 陆学文不由"
        },
        {
          "title": "逼我断亲睡破船，转身就赶海暴富",
          "intro": "【本文纯手搓，不AI，传统工艺，值得信赖】 【年代重生】【随身空间是大海】【空间椰子水治百病长神力】 牛八一重生回到被后妈逼着分家，只分到一条破船那天。 亲父完全站在后妈那边，对为这个家累得病倒在床的"
        }
      ],
      "top_risers": [
        {
          "title": "重生不当冤大头，校花你着急啥？",
          "change": "+5"
        },
        {
          "title": "七零，我的老婆是资本家大小姐",
          "change": "+2"
        },
        {
          "title": "狩猎北大荒：投亲路上遇到狼拦路",
          "change": "+1"
        }
      ],
      "top_fallers": [
        {
          "title": "八零年代：冒牌留子另类报国",
          "change": "-4"
        },
        {
          "title": "鬼才律师：劝人自首还被送锦旗？",
          "change": "-4"
        },
        {
          "title": "高二分科，我选校花也选亿万身家",
          "change": "-4"
        }
      ],
      "reads_growth": [
        {
          "title": "重生80，分家后带妻女吃香喝辣",
          "growth": "+2.3万"
        },
        {
          "title": "狩猎北大荒：投亲路上遇到狼拦路",
          "growth": "+5000"
        },
        {
          "title": "七零，我的老婆是资本家大小姐",
          "growth": "+5000"
        }
      ],
      "summary": "新增2本上榜；2本掉出（《60年代，为护着妹妹被迫下乡》、《逼我断亲睡破船，转身就赶海暴富》）；《重生不当冤大头，校花你着急啥？》排名上升+5位；《重生80，分家后带妻女吃香喝辣》阅读量+2.3万。"
    },
    "传统玄幻": {
      "new_count": 2,
      "dropped_count": 2,
      "new_books": [
        "玄幻反派：女主把握不住，让爹来",
        "大周靖妖监，开局合道之境！"
      ],
      "dropped_books": [
        {
          "title": "我只想毁灭宗门，咋逆天成神了",
          "intro": "重生天下第一宗，本该是完美开局。 可楚星河发现，自己的修行之路有点与众不同。 只要毁掉自家宗门就能天下无敌？ 建一个天下第一宗不容易，毁掉还不容易？ 楚星河发现还真不容易。 为搞垮自家宗门费尽心思，可"
        },
        {
          "title": "无敌皇子，开局迎娶女杀神",
          "intro": "叶枭，大乾三皇子，武道天资无敌，十四岁入江湖，一游十载。 得人皇传承，重归朝堂，欲掌皇权。 只是让他没想到的是刚刚还朝，便被赐婚，而赐婚对象，则是一位冒天下之大不讳，帝都人人谈而色变，屠敌数十万的女将"
        }
      ],
      "top_risers": [
        {
          "title": "大婚之日，我阉了未婚妻的白月光",
          "change": "+2"
        },
        {
          "title": "天赋无敌的我，一心只想苟活",
          "change": "+2"
        },
        {
          "title": "灵墟，剑棺，瞎剑客",
          "change": "+1"
        }
      ],
      "top_fallers": [
        {
          "title": "玄幻：逆命万世，我打爆仙帝",
          "change": "-2"
        },
        {
          "title": "仙子你听我解释",
          "change": "-2"
        },
        {
          "title": "邪鼎",
          "change": "-2"
        }
      ],
      "reads_growth": [
        {
          "title": "生死圣皇",
          "growth": "+1.8万"
        },
        {
          "title": "大婚之日，我阉了未婚妻的白月光",
          "growth": "+1.7万"
        },
        {
          "title": "北侯世子：反派的我背景逆天",
          "growth": "+1.2万"
        }
      ],
      "summary": "新增2本上榜；2本掉出（《我只想毁灭宗门，咋逆天成神了》、《无敌皇子，开局迎娶女杀神》）；《大婚之日，我阉了未婚妻的白月光》排名上升+2位；《生死圣皇》阅读量+1.8万。"
    },
    "历史脑洞": {
      "new_count": 2,
      "dropped_count": 2,
      "new_books": [
        "人在汉末：开局签到龙象般若",
        "现代牛马穿两界，开局就欠六个崽"
      ],
      "dropped_books": [
        {
          "title": "三国：好贤孙，曹魏可行三代！",
          "intro": "(评分刚出，后续会涨，请放心食用。) 开局系统跑路，曹魏，三国。 前期主要以曹家三代的日常，幽默搞笑为主，安稳发育，后期开始主线统一。 曹操:令君，诸子中谁可担大任? 荀彧:我觉得公子叡可以。 曹操:"
        },
        {
          "title": "我被老朱问斩，马皇后玉玺砸老朱",
          "intro": "他叫朱沐英。 一个穿越者，十五年前穿越到大明王朝，成为了朱元璋五子，英王朱沐英。 获得武神签到系统。 【第一年签到武神境。】 【第二年签到十万大雪龙骑。】 【第三年签到百万石粮草。】 【第四年武神境圆"
        }
      ],
      "top_risers": [
        {
          "title": "让你教太子，没让你教太子谋反",
          "change": "+6"
        },
        {
          "title": "三国：从陈王世子开始",
          "change": "+5"
        },
        {
          "title": "大唐：武才人？请陛下称太子侧妃",
          "change": "+4"
        }
      ],
      "top_fallers": [
        {
          "title": "让你改稻为桑，你把嘉靖气懵了！",
          "change": "-4"
        },
        {
          "title": "朕还没动手，董卓就成忠臣了？",
          "change": "-2"
        },
        {
          "title": "女帝宣战八国？我把她砍成臊子",
          "change": "-2"
        }
      ],
      "reads_growth": [
        {
          "title": "北宋年间一咸鱼",
          "growth": "+9000"
        },
        {
          "title": "一心求死，反倒成为千古一帝？",
          "growth": "+7000"
        },
        {
          "title": "大明日不落，开局治好马皇后",
          "growth": "+7000"
        }
      ],
      "summary": "新增2本上榜；2本掉出（《三国：好贤孙，曹魏可行三代！》、《我被老朱问斩，马皇后玉玺砸老朱》）；《让你教太子，没让你教太子谋反》排名上升+6位；《北宋年间一咸鱼》阅读量+9000。"
    },
    "悬疑脑洞": {
      "new_count": 1,
      "dropped_count": 1,
      "new_books": [
        "我沟通未来，杀穿这个末世！"
      ],
      "dropped_books": [
        {
          "title": "开局冥币亿万：诡异时代我无敌",
          "intro": "【诡异+末世+神豪+冥币+规则+搞笑+无女主+快节奏爽文（7章买下诡异场景，一路买买买不墨迹，二十万字买下整座城市）+中期反转+后期规则推理】 诡异末世降临，恶诡横行 在规则之内，诡无法杀人 当无数人"
        }
      ],
      "top_risers": [
        {
          "title": "穿成诡异后联盟派我去当boss",
          "change": "+2"
        },
        {
          "title": "回档求生：我真不是大佬啊",
          "change": "+2"
        },
        {
          "title": "那一天，月亮吞下整座城",
          "change": "+1"
        }
      ],
      "top_fallers": [
        {
          "title": "盗墓：人在九门，系统非说是洪荒",
          "change": "-3"
        },
        {
          "title": "宿舍求生，我被拉进了管理群",
          "change": "-2"
        },
        {
          "title": "疯了吧！地狱副本BOSS是萝莉",
          "change": "-2"
        }
      ],
      "reads_growth": [
        {
          "title": "疯了吧！地狱副本BOSS是萝莉",
          "growth": "+1.2万"
        },
        {
          "title": "全民求生：我在诡异末日养成少女",
          "growth": "+1.1万"
        },
        {
          "title": "十日终焉",
          "growth": "+4000"
        }
      ],
      "summary": "新增1本上榜；1本掉出（《开局冥币亿万：诡异时代我无敌》）；《穿成诡异后联盟派我去当boss》排名上升+2位；《疯了吧！地狱副本BOSS是萝莉》阅读量+1.2万。"
    },
    "都市脑洞": {
      "new_count": 1,
      "dropped_count": 1,
      "new_books": [
        "让我开早餐店？我下午才营业"
      ],
      "dropped_books": [
        {
          "title": "我只想当个小官",
          "intro": "我没有什么大志向，只是想安安稳稳的生活，没有什么大的追求，只想守好自己的一亩三分地，但时代变了，这个世界真真假假，黑白不分，竟然996是福报这种都能出现，这是离了个大普，我实在不想在这996混下去了，"
        }
      ],
      "top_risers": [
        {
          "title": "饰演封于修，女友神仙姐姐",
          "change": "+5"
        },
        {
          "title": "我，圈钱主播！但大哥是真刷啊！",
          "change": "+3"
        },
        {
          "title": "让你去潜伏，你把老米搬空了？",
          "change": "+2"
        }
      ],
      "top_fallers": [
        {
          "title": "参加个真人秀，怎么送我万民伞了",
          "change": "-5"
        },
        {
          "title": "发配东莞，被两个精神小妹崩了",
          "change": "-3"
        },
        {
          "title": "人在五哈：全网催我和前任复合！",
          "change": "-3"
        }
      ],
      "reads_growth": [
        {
          "title": "每天一个亿，开局和校花签订契约",
          "growth": "+2.4万"
        },
        {
          "title": "好感度系统：女神想要的，我全有",
          "growth": "+9000"
        },
        {
          "title": "每天六千万，只能在县城花？",
          "growth": "+5000"
        }
      ],
      "summary": "新增1本上榜；1本掉出（《我只想当个小官》）；《饰演封于修，女友神仙姐姐》排名上升+5位；《每天一个亿，开局和校花签订契约》阅读量+2.4万。"
    },
    "玄幻脑洞": {
      "new_count": 1,
      "dropped_count": 1,
      "new_books": [
        "开局娶丑妻，睡一天涨一年功力"
      ],
      "dropped_books": [
        {
          "title": "九恶妃每日一问，陛下驾崩了吗？",
          "intro": "【后宫】【多女】【昏君】【无敌】【爆爽】【多图】 我，网文作者，穿成了自己书中活不过50章的炮灰昏君。 皇权被九位绝色妃子架空，她们每天还变着法儿的折磨我。 今天种蛊，明天下毒，后天想把我炼成鼎炉……"
        }
      ],
      "top_risers": [
        {
          "title": "文字武侠：开局破庙夜会帮主夫人",
          "change": "+4"
        },
        {
          "title": "一日破五境，人间太岁神！",
          "change": "+3"
        },
        {
          "title": "提前登陆游戏世界，开局联姻女帝",
          "change": "+2"
        }
      ],
      "top_fallers": [
        {
          "title": "轮回万界，亿万神话词条加身！",
          "change": "-6"
        },
        {
          "title": "模拟长生，我能结算天赋词条",
          "change": "-4"
        },
        {
          "title": "命格大器晚成？可我是天才啊！",
          "change": "-1"
        }
      ],
      "reads_growth": [
        {
          "title": "这个游戏不对劲，我挖矿成神！",
          "growth": "+3.6万"
        },
        {
          "title": "从变身少女开始斩妖除魔",
          "growth": "+3.1万"
        },
        {
          "title": "提前登陆游戏世界，开局联姻女帝",
          "growth": "+2.5万"
        }
      ],
      "summary": "新增1本上榜；1本掉出（《九恶妃每日一问，陛下驾崩了吗？》）；《文字武侠：开局破庙夜会帮主夫人》排名上升+4位；《这个游戏不对劲，我挖矿成神！》阅读量+3.6万。"
    },
    "悬疑灵异": {
      "new_count": 0,
      "dropped_count": 0,
      "new_books": [],
      "dropped_books": [],
      "top_risers": [
        {
          "title": "什么叫我缝的尸体都是大凶之物？",
          "change": "+2"
        },
        {
          "title": "小道士陈不欺",
          "change": "+2"
        },
        {
          "title": "天师在此，奇门风水震天下",
          "change": "+1"
        }
      ],
      "top_fallers": [
        {
          "title": "小警大用",
          "change": "-3"
        },
        {
          "title": "从红溪村开始的僵尸生活",
          "change": "-2"
        },
        {
          "title": "九叔以为捡个小萌僵，结果是猛僵",
          "change": "-2"
        }
      ],
      "reads_growth": [
        {
          "title": "法医：与死者同行",
          "growth": "+2.4万"
        },
        {
          "title": "尸生子，鬼抬棺",
          "growth": "+7000"
        },
        {
          "title": "我，区区扎纸匠，你却让我办大案",
          "growth": "+6000"
        }
      ],
      "summary": "《什么叫我缝的尸体都是大凶之物？》排名上升+2位；《法医：与死者同行》阅读量+2.4万。"
    },
    "抗战谍战": {
      "new_count": 1,
      "dropped_count": 1,
      "new_books": [
        "神油"
      ],
      "dropped_books": [
        {
          "title": "我，奉化黄埔系，升职快点很合理",
          "intro": "【系统】+【民国】+【黄埔开局】+【杀伐果断】 【中原大战写的有问题，可跳过从第44章开始，后面的内容不会让大家失望的。】 【已升任军长，铨叙陆军中将，三十一岁，部队番号为中央警卫军，已经进入兰封会战"
        }
      ],
      "top_risers": [
        {
          "title": "抗日先遣：我率红七军团兵临南京",
          "change": "+7"
        },
        {
          "title": "亮剑，旅长恭喜我发财",
          "change": "+2"
        },
        {
          "title": "谍战：开局偷听心声，识破日谍",
          "change": "+2"
        }
      ],
      "top_fallers": [
        {
          "title": "黄埔第一毒士，宋家小妹倒追",
          "change": "-5"
        },
        {
          "title": "开局桂系，我要下南洋",
          "change": "-2"
        },
        {
          "title": "亮剑：人在新二团，专治火力不足",
          "change": "-2"
        }
      ],
      "reads_growth": [
        {
          "title": "抗日先遣：我率红七军团兵临南京",
          "growth": "+2.3万"
        },
        {
          "title": "抗战，他们都叫我炮神",
          "growth": "+8000"
        },
        {
          "title": "亮剑：独自发展，我真不想当大帅",
          "growth": "+7000"
        }
      ],
      "summary": "新增1本上榜；1本掉出（《我，奉化黄埔系，升职快点很合理》）；《抗日先遣：我率红七军团兵临南京》排名上升+7位；《抗日先遣：我率红七军团兵临南京》阅读量+2.3万。"
    },
    "游戏体育": {
      "new_count": 1,
      "dropped_count": 1,
      "new_books": [
        "詹姆斯跑路？反手梭哈库里"
      ],
      "dropped_books": [
        {
          "title": "顶级奸商：无敌从贩卖军火开始",
          "intro": "【传统网游】+【重生】+【无女主】+【赚钱】 网游：【天下】开服，林风带着上一世的记忆，转职奸商。 为了赚到五十万拼命努力，却没想到……一不小心赚多了。 “我不在江湖，江湖全都是我的传说。” “没有什"
        }
      ],
      "top_risers": [
        {
          "title": "无畏契约：我依旧是世一决",
          "change": "+3"
        },
        {
          "title": "全民迷雾求生",
          "change": "+2"
        },
        {
          "title": "网游：我有超神级天赋",
          "change": "+2"
        }
      ],
      "top_fallers": [
        {
          "title": "足球：开局被断腿，搭档哈兰德！",
          "change": "-11"
        },
        {
          "title": "带C罗横扫美加墨世界杯！",
          "change": "-3"
        },
        {
          "title": "开局强化癌细胞，我独获登神序列",
          "change": "-3"
        }
      ],
      "reads_growth": [
        {
          "title": "网游：无垠无尽之主",
          "growth": "+1.9万"
        },
        {
          "title": "游戏入侵：我一路杀到诸神颤抖",
          "growth": "+3000"
        },
        {
          "title": "木屋求生：我出生在刷怪笼旁",
          "growth": "+3000"
        }
      ],
      "summary": "新增1本上榜；1本掉出（《顶级奸商：无敌从贩卖军火开始》）；《无畏契约：我依旧是世一决》排名上升+3位；《网游：无垠无尽之主》阅读量+1.9万。"
    },
    "动漫衍生": {
      "new_count": 2,
      "dropped_count": 2,
      "new_books": [
        "美漫：国产凌凌漆，开局上交变种",
        "奥特曼：我，究极海帕杰顿"
      ],
      "dropped_books": [
        {
          "title": "宝可梦：我玩钢的",
          "intro": "世家+钢系+异色巨金怪+顶级天赋+无女主+系统 夏桀：你寒窗苦读二十年，我世家积累一千年。 爷爷是夏家家主，夏国准冠军巅峰，父亲是鎏金省训练家协会会长。 夏桀出生就觉醒完美钢之心，可以加速钢系宝可梦的"
        },
        {
          "title": "海贼：我，艾斯，日蚀之王！",
          "intro": "穿越成海贼王罗杰的血脉，波特卡斯·D·艾斯？ 想到未来要去给白胡子当乖儿子，最后还要被赤犬一拳穿胸？ 抱歉，去他妈的剧情杀！ 这一世，灵魂异变，天生完美双果实位！ 左手暗暗果实吞噬万物，右手朱雀神火焚"
        }
      ],
      "top_risers": [
        {
          "title": "大角牛负责领，我贝利亚负责养",
          "change": "+4"
        },
        {
          "title": "让蛇叔当火影，木叶早玩上手游了",
          "change": "+4"
        },
        {
          "title": "我，恶霸蜘蛛侠，打爆漫威！",
          "change": "+4"
        }
      ],
      "top_fallers": [
        {
          "title": "海贼：玛丽乔亚的王族宇智波！",
          "change": "-8"
        },
        {
          "title": "聊天群里的光之巨人",
          "change": "-3"
        },
        {
          "title": "RE0：刚出便利店就是贤者之塔",
          "change": "-2"
        }
      ],
      "reads_growth": [
        {
          "title": "综漫：留学千叶的我兼职光之巨人",
          "growth": "+2.4万"
        },
        {
          "title": "叫你拍特摄，你真去当奥特曼了？",
          "growth": "+1.7万"
        },
        {
          "title": "我，恶霸蜘蛛侠，打爆漫威！",
          "growth": "+1.6万"
        }
      ],
      "summary": "新增2本上榜；2本掉出（《宝可梦：我玩钢的》、《海贼：我，艾斯，日蚀之王！》）；《大角牛负责领，我贝利亚负责养》排名上升+4位；《综漫：留学千叶的我兼职光之巨人》阅读量+2.4万。"
    },
    "男频衍生": {
      "new_count": 1,
      "dropped_count": 1,
      "new_books": [
        "新三国怪谈：开局扮演面瘫刘备"
      ],
      "dropped_books": [
        {
          "title": "名义：家父赵德汉，我望父成龙！",
          "intro": "一觉醒来，发现自己穿越到了《人民的名义》当中。 我爹，赵德汉？ 一定要守住底线，这辈子要清清白白。 什么？我爹要空降汉东？ 好，真好！ 给汉东投资，推动汉东省的经济发展。 赵德汉：儿砸，你这个智能手机"
        }
      ],
      "top_risers": [
        {
          "title": "四合院：开局保卫处，海中叫我叔",
          "change": "+18"
        },
        {
          "title": "名义：工作的时候称职务",
          "change": "+3"
        },
        {
          "title": "港综，十三妹是我大佬",
          "change": "+2"
        }
      ],
      "top_fallers": [
        {
          "title": "四合院：秦淮茹赖上我",
          "change": "-4"
        },
        {
          "title": "卧底十年，我不装了",
          "change": "-4"
        },
        {
          "title": "傻柱重生四合院：从敲闷棍开始",
          "change": "-2"
        }
      ],
      "reads_growth": [
        {
          "title": "四合院：开局保卫处，海中叫我叔",
          "growth": "+5.5万"
        },
        {
          "title": "四合院：舅舅易中海，我来享福啦",
          "growth": "+1.0万"
        },
        {
          "title": "穿越港综，从解锁各路美女开始",
          "growth": "+9000"
        }
      ],
      "summary": "新增1本上榜；1本掉出（《名义：家父赵德汉，我望父成龙！》）；《四合院：开局保卫处，海中叫我叔》排名上升+18位；《四合院：开局保卫处，海中叫我叔》阅读量+5.5万。"
    }
  }
}