{
  "date": "2026-07-12",
  "list_key": "male_read",
  "list_name": "男频阅读榜",
  "category_reads": [
    {
      "category": "都市高武",
      "total_reads": 18612000,
      "reads_str": "1861.2万",
      "book_count": 30,
      "max_reads": 2578000,
      "min_reads": 271000,
      "avg_reads": 620400
    },
    {
      "category": "玄幻脑洞",
      "total_reads": 13318364,
      "reads_str": "1331.8万",
      "book_count": 30,
      "max_reads": 1646000,
      "min_reads": 3364,
      "avg_reads": 443945
    },
    {
      "category": "都市脑洞",
      "total_reads": 13022000,
      "reads_str": "1302.2万",
      "book_count": 30,
      "max_reads": 1193000,
      "min_reads": 274000,
      "avg_reads": 434067
    },
    {
      "category": "都市日常",
      "total_reads": 12060000,
      "reads_str": "1206.0万",
      "book_count": 30,
      "max_reads": 1082000,
      "min_reads": 243000,
      "avg_reads": 402000
    },
    {
      "category": "历史古代",
      "total_reads": 10577000,
      "reads_str": "1057.7万",
      "book_count": 30,
      "max_reads": 1262000,
      "min_reads": 154000,
      "avg_reads": 352567
    },
    {
      "category": "悬疑脑洞",
      "total_reads": 10238000,
      "reads_str": "1023.8万",
      "book_count": 30,
      "max_reads": 2536000,
      "min_reads": 130000,
      "avg_reads": 341267
    },
    {
      "category": "传统玄幻",
      "total_reads": 9555000,
      "reads_str": "955.5万",
      "book_count": 30,
      "max_reads": 1225000,
      "min_reads": 149000,
      "avg_reads": 318500
    },
    {
      "category": "东方仙侠",
      "total_reads": 7330000,
      "reads_str": "733.0万",
      "book_count": 30,
      "max_reads": 725000,
      "min_reads": 152000,
      "avg_reads": 244333
    },
    {
      "category": "男频衍生",
      "total_reads": 7253000,
      "reads_str": "725.3万",
      "book_count": 30,
      "max_reads": 459000,
      "min_reads": 154000,
      "avg_reads": 241767
    },
    {
      "category": "悬疑灵异",
      "total_reads": 7148000,
      "reads_str": "714.8万",
      "book_count": 30,
      "max_reads": 804000,
      "min_reads": 112000,
      "avg_reads": 238267
    },
    {
      "category": "都市修真",
      "total_reads": 6535000,
      "reads_str": "653.5万",
      "book_count": 30,
      "max_reads": 562000,
      "min_reads": 123000,
      "avg_reads": 217833
    },
    {
      "category": "游戏体育",
      "total_reads": 6112000,
      "reads_str": "611.2万",
      "book_count": 30,
      "max_reads": 529000,
      "min_reads": 106000,
      "avg_reads": 203733
    },
    {
      "category": "科幻末世",
      "total_reads": 6064000,
      "reads_str": "606.4万",
      "book_count": 30,
      "max_reads": 746000,
      "min_reads": 120000,
      "avg_reads": 202133
    },
    {
      "category": "历史脑洞",
      "total_reads": 5836000,
      "reads_str": "583.6万",
      "book_count": 30,
      "max_reads": 497000,
      "min_reads": 108000,
      "avg_reads": 194533
    },
    {
      "category": "都市种田",
      "total_reads": 5519000,
      "reads_str": "551.9万",
      "book_count": 30,
      "max_reads": 313000,
      "min_reads": 131000,
      "avg_reads": 183967
    },
    {
      "category": "动漫衍生",
      "total_reads": 5071000,
      "reads_str": "507.1万",
      "book_count": 30,
      "max_reads": 407000,
      "min_reads": 124000,
      "avg_reads": 169033
    },
    {
      "category": "抗战谍战",
      "total_reads": 4769000,
      "reads_str": "476.9万",
      "book_count": 30,
      "max_reads": 470000,
      "min_reads": 92000,
      "avg_reads": 158967
    },
    {
      "category": "西方奇幻",
      "total_reads": 4306000,
      "reads_str": "430.6万",
      "book_count": 30,
      "max_reads": 434000,
      "min_reads": 77000,
      "avg_reads": 143533
    },
    {
      "category": "战神赘婿",
      "total_reads": 2684000,
      "reads_str": "268.4万",
      "book_count": 30,
      "max_reads": 207000,
      "min_reads": 45000,
      "avg_reads": 89467
    }
  ],
  "top_books": [
    {
      "title": "我不是戏神",
      "author": "三九音域",
      "category": "都市高武",
      "reads": 2578000.0,
      "reads_str": "257.8万",
      "url": "https://fanqienovel.com/page/7276384138653862966"
    },
    {
      "title": "十日终焉",
      "author": "杀虫队队员",
      "category": "悬疑脑洞",
      "reads": 2536000.0,
      "reads_str": "253.6万",
      "url": "https://fanqienovel.com/page/7143038691944959011"
    },
    {
      "title": "我在精神病院学斩神",
      "author": "三九音域",
      "category": "都市高武",
      "reads": 1837000.0,
      "reads_str": "183.7万",
      "url": "https://fanqienovel.com/page/6982529841564224526"
    },
    {
      "title": "这个游戏不对劲，我挖矿成神！",
      "author": "道不易",
      "category": "玄幻脑洞",
      "reads": 1646000.0,
      "reads_str": "164.6万",
      "url": "https://fanqienovel.com/page/7590221243043826712"
    },
    {
      "title": "时停起手，邪神也得给我跪下！",
      "author": "六个葫芦",
      "category": "都市高武",
      "reads": 1370000.0,
      "reads_str": "137万",
      "url": "https://fanqienovel.com/page/7504849932138859545"
    },
    {
      "title": "皇家金牌县令",
      "author": "板面王仔",
      "category": "历史古代",
      "reads": 1262000.0,
      "reads_str": "126.2万",
      "url": "https://fanqienovel.com/page/7046842344074644484"
    },
    {
      "title": "惊鸿",
      "author": "一夕烟雨",
      "category": "传统玄幻",
      "reads": 1225000.0,
      "reads_str": "122.5万",
      "url": "https://fanqienovel.com/page/6883748331202284558"
    },
    {
      "title": "归国留洋水货？叫我芯片之父！",
      "author": "这肉有毒",
      "category": "都市脑洞",
      "reads": 1193000.0,
      "reads_str": "119.3万",
      "url": "https://fanqienovel.com/page/7623581376586976281"
    },
    {
      "title": "我操作的少女正在成为旧日之主",
      "author": "陷阵营营长",
      "category": "都市高武",
      "reads": 1094000.0,
      "reads_str": "109.4万",
      "url": "https://fanqienovel.com/page/7592279900040465433"
    },
    {
      "title": "天眼风水师",
      "author": "道之光",
      "category": "都市日常",
      "reads": 1082000.0,
      "reads_str": "108.2万",
      "url": "https://fanqienovel.com/page/7326876174989134910"
    },
    {
      "title": "我家世代提刀，到我这儿提笔了！",
      "author": "牧野横舟",
      "category": "历史古代",
      "reads": 1072000.0,
      "reads_str": "107.2万",
      "url": "https://fanqienovel.com/page/7623459019432152089"
    },
    {
      "title": "诡舍",
      "author": "夜来风雨声丶",
      "category": "悬疑脑洞",
      "reads": 1030000.0,
      "reads_str": "103万",
      "url": "https://fanqienovel.com/page/7256784068786785336"
    },
    {
      "title": "天渊",
      "author": "沐潇三生",
      "category": "传统玄幻",
      "reads": 1001000.0,
      "reads_str": "100.1万",
      "url": "https://fanqienovel.com/page/7138249318909086727"
    },
    {
      "title": "诸神愚戏",
      "author": "一月九十秋",
      "category": "都市高武",
      "reads": 960000.0,
      "reads_str": "96万",
      "url": "https://fanqienovel.com/page/7338034838672247833"
    },
    {
      "title": "序列：吃神者",
      "author": "不要大脑要小脑",
      "category": "都市高武",
      "reads": 863000.0,
      "reads_str": "86.3万",
      "url": "https://fanqienovel.com/page/7346057588347259929"
    },
    {
      "title": "开局长生万古，苟到天荒地老",
      "author": "紫灵风雪",
      "category": "玄幻脑洞",
      "reads": 856000.0,
      "reads_str": "85.6万",
      "url": "https://fanqienovel.com/page/7147596144942517284"
    },
    {
      "title": "大一实习，你跑去749收容怪物",
      "author": "我爱罗的沙",
      "category": "都市高武",
      "reads": 841000.0,
      "reads_str": "84.1万",
      "url": "https://fanqienovel.com/page/7421167583522458648"
    },
    {
      "title": "系统赋我长生，我熬死了所有人",
      "author": "一只榴莲3号",
      "category": "玄幻脑洞",
      "reads": 829000.0,
      "reads_str": "82.9万",
      "url": "https://fanqienovel.com/page/7228940788351110182"
    },
    {
      "title": "我以狐仙镇百鬼",
      "author": "紫梦游龙",
      "category": "悬疑灵异",
      "reads": 804000.0,
      "reads_str": "80.4万",
      "url": "https://fanqienovel.com/page/7087872099557051400"
    },
    {
      "title": "线上腹黑游戏姐，线下高冷女教授",
      "author": "杯酒宿醉",
      "category": "都市日常",
      "reads": 753000.0,
      "reads_str": "75.3万",
      "url": "https://fanqienovel.com/page/7636969790375988286"
    }
  ],
  "total_categories": 19,
  "total_books": 570,
  "trend_7d": []
}