{
  "date": "2026-07-13",
  "list_key": "male_new",
  "list_name": "男频新书榜",
  "category_reads": [
    {
      "category": "都市脑洞",
      "total_reads": 7567000,
      "reads_str": "756.7万",
      "book_count": 30,
      "max_reads": 748000,
      "min_reads": 96000,
      "avg_reads": 252233
    },
    {
      "category": "都市高武",
      "total_reads": 4546000,
      "reads_str": "454.6万",
      "book_count": 30,
      "max_reads": 438000,
      "min_reads": 62000,
      "avg_reads": 151533
    },
    {
      "category": "动漫衍生",
      "total_reads": 4179000,
      "reads_str": "417.9万",
      "book_count": 30,
      "max_reads": 337000,
      "min_reads": 77000,
      "avg_reads": 139300
    },
    {
      "category": "玄幻脑洞",
      "total_reads": 4175000,
      "reads_str": "417.5万",
      "book_count": 30,
      "max_reads": 466000,
      "min_reads": 59000,
      "avg_reads": 139167
    },
    {
      "category": "男频衍生",
      "total_reads": 4074000,
      "reads_str": "407.4万",
      "book_count": 30,
      "max_reads": 326000,
      "min_reads": 84000,
      "avg_reads": 135800
    },
    {
      "category": "都市日常",
      "total_reads": 3919000,
      "reads_str": "391.9万",
      "book_count": 30,
      "max_reads": 281000,
      "min_reads": 69000,
      "avg_reads": 130633
    },
    {
      "category": "历史脑洞",
      "total_reads": 3041000,
      "reads_str": "304.1万",
      "book_count": 30,
      "max_reads": 313000,
      "min_reads": 55000,
      "avg_reads": 101367
    },
    {
      "category": "都市修真",
      "total_reads": 2594000,
      "reads_str": "259.4万",
      "book_count": 30,
      "max_reads": 267000,
      "min_reads": 24000,
      "avg_reads": 86467
    },
    {
      "category": "都市种田",
      "total_reads": 2518000,
      "reads_str": "251.8万",
      "book_count": 30,
      "max_reads": 254000,
      "min_reads": 35000,
      "avg_reads": 83933
    },
    {
      "category": "抗战谍战",
      "total_reads": 2220000,
      "reads_str": "222.0万",
      "book_count": 30,
      "max_reads": 199000,
      "min_reads": 32000,
      "avg_reads": 74000
    },
    {
      "category": "悬疑脑洞",
      "total_reads": 2191000,
      "reads_str": "219.1万",
      "book_count": 30,
      "max_reads": 287000,
      "min_reads": 30000,
      "avg_reads": 73033
    },
    {
      "category": "东方仙侠",
      "total_reads": 2005000,
      "reads_str": "200.5万",
      "book_count": 30,
      "max_reads": 155000,
      "min_reads": 34000,
      "avg_reads": 66833
    },
    {
      "category": "科幻末世",
      "total_reads": 1999000,
      "reads_str": "199.9万",
      "book_count": 30,
      "max_reads": 230000,
      "min_reads": 30000,
      "avg_reads": 66633
    },
    {
      "category": "游戏体育",
      "total_reads": 1773000,
      "reads_str": "177.3万",
      "book_count": 30,
      "max_reads": 138000,
      "min_reads": 34000,
      "avg_reads": 59100
    },
    {
      "category": "西方奇幻",
      "total_reads": 1536000,
      "reads_str": "153.6万",
      "book_count": 30,
      "max_reads": 133000,
      "min_reads": 22000,
      "avg_reads": 51200
    },
    {
      "category": "历史古代",
      "total_reads": 1430000,
      "reads_str": "143.0万",
      "book_count": 30,
      "max_reads": 126000,
      "min_reads": 21000,
      "avg_reads": 47667
    },
    {
      "category": "传统玄幻",
      "total_reads": 1284000,
      "reads_str": "128.4万",
      "book_count": 30,
      "max_reads": 316000,
      "min_reads": 11000,
      "avg_reads": 42800
    },
    {
      "category": "悬疑灵异",
      "total_reads": 1239000,
      "reads_str": "123.9万",
      "book_count": 30,
      "max_reads": 299000,
      "min_reads": 13000,
      "avg_reads": 41300
    },
    {
      "category": "战神赘婿",
      "total_reads": 312002,
      "reads_str": "31.2万",
      "book_count": 30,
      "max_reads": 28000,
      "min_reads": 2256,
      "avg_reads": 10400
    }
  ],
  "top_books": [
    {
      "title": "实习教出金牌班，家长要换班主任",
      "author": "碧水红潮",
      "category": "都市脑洞",
      "reads": 748000.0,
      "reads_str": "74.8万",
      "url": "https://fanqienovel.com/page/7649016386907278361"
    },
    {
      "title": "高考出分前一晚，兑换北大录取书",
      "author": "西瓜要涨价",
      "category": "都市脑洞",
      "reads": 671000.0,
      "reads_str": "67.1万",
      "url": "https://fanqienovel.com/page/7650159645603941438"
    },
    {
      "title": "上恋综后，和清冷设计师爆火全网",
      "author": "在下张滚滚",
      "category": "都市脑洞",
      "reads": 477000.0,
      "reads_str": "47.7万",
      "url": "https://fanqienovel.com/page/7641906591557487640"
    },
    {
      "title": "从成为一只白鹿开始的传说",
      "author": "早醒的天蝎",
      "category": "玄幻脑洞",
      "reads": 466000.0,
      "reads_str": "46.6万",
      "url": "https://fanqienovel.com/page/7652903442444192792"
    },
    {
      "title": "我都宇宙之主了，你们还在地球？",
      "author": "吒牛",
      "category": "都市高武",
      "reads": 438000.0,
      "reads_str": "43.8万",
      "url": "https://fanqienovel.com/page/7644040936980220953"
    },
    {
      "title": "下载APP，才发现青梅好感爆了",
      "author": "八音",
      "category": "都市脑洞",
      "reads": 419000.0,
      "reads_str": "41.9万",
      "url": "https://fanqienovel.com/page/7638459797838236696"
    },
    {
      "title": "我一写网文的，你让我混娱乐圈？",
      "author": "淮海养鸡人",
      "category": "都市脑洞",
      "reads": 343000.0,
      "reads_str": "34.3万",
      "url": "https://fanqienovel.com/page/7571820285721054233"
    },
    {
      "title": "都要退圈了，你演唱会唱这么红？",
      "author": "脑子有点馋",
      "category": "都市脑洞",
      "reads": 338000.0,
      "reads_str": "33.8万",
      "url": "https://fanqienovel.com/page/7635455897451383833"
    },
    {
      "title": "一人：武侯奇门不在奇门，在武侯",
      "author": "拉过勾的事",
      "category": "动漫衍生",
      "reads": 337000.0,
      "reads_str": "33.7万",
      "url": "https://fanqienovel.com/page/7652679044999171134"
    },
    {
      "title": "龙族：坏了！路明非得了抑郁症",
      "author": "献给某人的花束",
      "category": "男频衍生",
      "reads": 326000.0,
      "reads_str": "32.6万",
      "url": "https://fanqienovel.com/page/7629649924644162584"
    },
    {
      "title": "开局法相，未婚妻不退婚",
      "author": "月哓",
      "category": "传统玄幻",
      "reads": 316000.0,
      "reads_str": "31.6万",
      "url": "https://fanqienovel.com/page/7641553002393766936"
    },
    {
      "title": "开局破解支付宝，疯狂得吃少御萝",
      "author": "可乐口可",
      "category": "都市脑洞",
      "reads": 316000.0,
      "reads_str": "31.6万",
      "url": "https://fanqienovel.com/page/7641906291819940926"
    },
    {
      "title": "什么叫高考满分，但人失踪了？",
      "author": "核动力打窝仙人",
      "category": "都市脑洞",
      "reads": 315000.0,
      "reads_str": "31.5万",
      "url": "https://fanqienovel.com/page/7647411499236871230"
    },
    {
      "title": "开局拜入圣地，发现祖上是人皇！",
      "author": "我爱码字我爱写作",
      "category": "玄幻脑洞",
      "reads": 314000.0,
      "reads_str": "31.4万",
      "url": "https://fanqienovel.com/page/7645931910685805630"
    },
    {
      "title": "大秦我带秦始皇长生不老",
      "author": "快乐的守村人",
      "category": "历史脑洞",
      "reads": 313000.0,
      "reads_str": "31.3万",
      "url": "https://fanqienovel.com/page/7645220011115547710"
    },
    {
      "title": "晚年大帝，被妹妹召唤国运求生？",
      "author": "七十岁殿堂之资",
      "category": "都市高武",
      "reads": 307000.0,
      "reads_str": "30.7万",
      "url": "https://fanqienovel.com/page/7652308382908419096"
    },
    {
      "title": "第一次破译免费？反手破译系统！",
      "author": "我不吃牛肉c",
      "category": "都市高武",
      "reads": 300000.0,
      "reads_str": "30万",
      "url": "https://fanqienovel.com/page/7633400795525811262"
    },
    {
      "title": "完美犯罪？在我的眼里全是破绽！",
      "author": "只抽半颗烟的老登",
      "category": "悬疑灵异",
      "reads": 299000.0,
      "reads_str": "29.9万",
      "url": "https://fanqienovel.com/page/7637415246868515902"
    },
    {
      "title": "跑男：白露作妖，我不吃压力",
      "author": "吃口白面包",
      "category": "都市脑洞",
      "reads": 289000.0,
      "reads_str": "28.9万",
      "url": "https://fanqienovel.com/page/7647522218607381566"
    },
    {
      "title": "我创立的组织，被重生者曝光了！",
      "author": "突兔兔",
      "category": "悬疑脑洞",
      "reads": 287000.0,
      "reads_str": "28.7万",
      "url": "https://fanqienovel.com/page/7649178879772347416"
    }
  ],
  "total_categories": 19,
  "total_books": 570,
  "trend_7d": []
}